
[
   {
      "DisplayImage": "MyimageDef",
      "Username": "MyName",
      "DisplayName": "JesusName",
      "Password": "Password123"
   },
   {
      "DisplayImage": "MyimageKat",
      "Username": "Spooodon",
      "DisplayName": "London",
      "Password": "Password"
   },
   {
      "DisplayImage": "MyimageTja",
      "Username": "Tobbbbeeee",
      "DisplayName": "Rot",
      "Password": "Dont"
   },
   {
      "DisplayImage": "MyimageChooo",
      "Username": "AlexS",
      "DisplayName": "BigSol",
      "Password": "MyFuntime"
   }
]

